{
    "rules": {
        "align": [
            true,
            "parameters"
        ],
        "class-name": true,
        "comment-format": [
            true,
            "check-space"
        ],
        "one-line": [
            true,
            "check-open-brace",
            "check-whitespace"
        ],
        "no-var-keyword": true,
        "jsdoc-format": true,
        "curly": true,
        "eofline": true,
        "forin": true,
        "indent": [
            true,
            "spaces"
        ],
        "label-position": true,
        "max-line-length": [
            true,
            160
        ],
        "member-ordering": [
            true,
            "public-before-private",
            "static-before-instance",
            "variables-before-functions"
        ],
        "no-arg": true,
        "no-bitwise": true,
        "no-console": [
            true,
            "debug",
            "info",
            "time",
            "timeEnd",
            "trace"
        ],
        "no-construct": true,
        "no-debugger": true,
        "no-duplicate-variable": true,
        "no-empty": false,
        "no-eval": true,
        "no-inferrable-types": [
            true,
            "ignore-params"
        ],
        "no-shadowed-variable": true,
        "no-string-literal": false,
        "no-switch-case-fall-through": true,
        "no-unused-expression": false,
        "quotemark": [
            true,
            "single",
            "avoid-escape"
        ],
        "radix": true,
        "semicolon": [
            true,
            "always",
            "ignore-bound-class-methods"
        ],
        "triple-equals": [
            true,
            "allow-null-check"
        ],
        "typedef": [
            true,
            "call-signature",
            "parameter"
        ],
        "variable-name": false,
        "trailing-comma": [
            true,
            {
                "multiline": "never",
                "singleline": "never"
            }
        ],
        "whitespace": [
            true,
            "check-branch",
            "check-decl",
            "check-operator",
            "check-module",
            "check-separator",
            "check-type"
        ],
        "typedef-whitespace": [
            true,
            {
                "call-signature": "nospace",
                "index-signature": "nospace",
                "parameter": "nospace",
                "property-declaration": "nospace",
                "variable-declaration": "nospace"
            },
            {
                "call-signature": "onespace",
                "index-signature": "onespace",
                "parameter": "onespace",
                "property-declaration": "onespace",
                "variable-declaration": "onespace"
            }
        ],
        "no-internal-module": true,
        "no-trailing-whitespace": true,
        "no-null-keyword": false,
        "prefer-const": true
    }
}
